kadaptest6/__init__.py
kadaptest6/data.py
kadaptest6/linked/__init__.py
kadaptest6/linked/bicycle.py
kadaptest6/linked/child.py
kadaptest6/linked/city.py
kadaptest6/linked/freezing.py
kadaptest6/linked/holiday.py
kadaptest6/linked/jaywalking.py
kadaptest6/linked/local.py
kadaptest6/linked/motorcycle.py
kadaptest6/linked/oldman.py
kadaptest6/linked/schoolzone.py
kadaptest6/linked/violation.py
kadaptest6/retained/__init__.py
kadaptest6/retained/retained.py
kadaptest6/retained/files/__init__.py
kadaptest6/vin_decoder/__init__.py
kadaptest6/vin_decoder/decoder.py
kadaptest7/__init__.py
kadaptest7/data.py
kadaptest7/linked/__init__.py
kadaptest7/linked/bicycle.py
kadaptest7/linked/child.py
kadaptest7/linked/city.py
kadaptest7/linked/freezing.py
kadaptest7/linked/holiday.py
kadaptest7/linked/jaywalking.py
kadaptest7/linked/local.py
kadaptest7/linked/motorcycle.py
kadaptest7/linked/oldman.py
kadaptest7/linked/schoolzone.py
kadaptest7/linked/violation.py
kadaptest7/retained/__init__.py
kadaptest7/retained/retained.py
kadaptest7/retained/files/__init__.py
kadaptest7/vin_decoder/__init__.py
kadaptest7/vin_decoder/decoder.py
kadaptest7-0.0.2.dist-info/LICENSE
kadaptest7-0.0.2.dist-info/METADATA
kadaptest7-0.0.2.dist-info/WHEEL
kadaptest7-0.0.2.dist-info/top_level.txt
kadaptest7-0.0.2.dist-info/RECORD
